LICENSE
setup.py
maisaedu_poormans_dms/__init__.py
maisaedu_poormans_dms/sql_server_migration.py
maisaedu_poormans_dms.egg-info/PKG-INFO
maisaedu_poormans_dms.egg-info/SOURCES.txt
maisaedu_poormans_dms.egg-info/dependency_links.txt
maisaedu_poormans_dms.egg-info/requires.txt
maisaedu_poormans_dms.egg-info/top_level.txt
maisaedu_poormans_dms/postgres_migration/Migrator.py
maisaedu_poormans_dms/postgres_migration/MigratorTable.py
maisaedu_poormans_dms/postgres_migration/__init__.py
maisaedu_poormans_dms/postgres_migration/Contracts/MigratorInterface.py
maisaedu_poormans_dms/postgres_migration/Contracts/MigratorRowInterface.py
maisaedu_poormans_dms/postgres_migration/Contracts/MigratorRowReaderInterface.py
maisaedu_poormans_dms/postgres_migration/Contracts/MigratorRowWriterInterface.py
maisaedu_poormans_dms/postgres_migration/Contracts/MigratorTableInterface.py
maisaedu_poormans_dms/postgres_migration/Contracts/__init__.py
maisaedu_poormans_dms/postgres_migration/MigratorRow/MigratorRow.py
maisaedu_poormans_dms/postgres_migration/MigratorRow/Reader.py
maisaedu_poormans_dms/postgres_migration/MigratorRow/Writer.py
maisaedu_poormans_dms/postgres_migration/MigratorRow/__init__.py
maisaedu_poormans_dms/redshift_dynamo_migration/Connector.py
maisaedu_poormans_dms/redshift_dynamo_migration/DynamoReplicator.py
maisaedu_poormans_dms/redshift_dynamo_migration/__init__.py
maisaedu_poormans_dms/redshift_dynamo_migration/Writer/WriterCDC.py
maisaedu_poormans_dms/redshift_dynamo_migration/Writer/WriterFull.py
maisaedu_poormans_dms/redshift_dynamo_migration/Writer/__init__.py
maisaedu_poormans_dms/redshift_dynamo_migration/models/Struct.py
maisaedu_poormans_dms/redshift_dynamo_migration/models/__init__.py
maisaedu_poormans_dms/redshift_dynamo_migration/services/Struct.py
maisaedu_poormans_dms/redshift_dynamo_migration/services/__init__.py
maisaedu_poormans_dms/redshift_migration/Connector.py
maisaedu_poormans_dms/redshift_migration/Logger.py
maisaedu_poormans_dms/redshift_migration/MigratorRedshift.py
maisaedu_poormans_dms/redshift_migration/Types.py
maisaedu_poormans_dms/redshift_migration/__init__.py
maisaedu_poormans_dms/redshift_migration/Contracts/ReaderInterface.py
