Metadata-Version: 2.1
Name: maisaedu-poormans-dms
Version: 1.2.73
Summary: A library for making database migration tasks, for +A Education
Home-page: UNKNOWN
Author: A+ Educação
Author-email: dataeng@maisaedu.com.br
License: MIT License
Platform: UNKNOWN
License-File: LICENSE
